MANIFEST.in
README.rst
TITLE.txt
lh-agpl3-LICENSE.txt
setup.py
./bin/rinvoker.py
./bin/wsInvokerIcmExamples.py
unisos/__init__.py
unisos.wsInvokerIcm.egg-info/PKG-INFO
unisos.wsInvokerIcm.egg-info/SOURCES.txt
unisos.wsInvokerIcm.egg-info/dependency_links.txt
unisos.wsInvokerIcm.egg-info/namespace_packages.txt
unisos.wsInvokerIcm.egg-info/not-zip-safe
unisos.wsInvokerIcm.egg-info/requires.txt
unisos.wsInvokerIcm.egg-info/top_level.txt
unisos/wsInvokerIcm/__init__.py
unisos/wsInvokerIcm/wsInvokerIcm.py